{
  "date": "2026-05-26",
  "fetched_at": "2026-05-26T21:11:21.217127+07:00",
  "results": {
    "535": [
      {
        "id": "00664",
        "date": "2026-05-26",
        "time": "21:00",
        "result": [
          14,
          15,
          22,
          24,
          33,
          3
        ]
      },
      {
        "id": "00663",
        "date": "2026-05-26",
        "time": "13:00",
        "result": [
          4,
          9,
          17,
          26,
          31,
          12
        ]
      }
    ],
    "645": [],
    "655": []
  }
}